[
	
	
	{
		"appIcon": "https://lh3.googleusercontent.com/CbfwEVaKZ5KCgYaUoPFUCA7hmcmWko56q69Tp_YTja7mka-8sLkBTtGyw2av1BNeT7g=s180",
		"appName": "Computer Shortcut Keys",
		"appDescription": "Computer Shortcut keys are generally required for using to use the computers or PC users were fast.",
		"url": "https://play.google.com/store/apps/details?id=com.shortcut.keys.computer"
	},
	{
		"appIcon": "https://lh3.googleusercontent.com/t5UyprTB-jUJk1VpB0IIVFQ134CLOwyktelkE8mqjkZ9vBNdmNCETAVeWjgSwnf8PQc=s180-rw",
		"appName": "Desi Maal Hot Photo",
		"appDescription": "HD Indian Hot Girls Photo & Wallpapers",
		"url": "https://play.google.com/store/apps/details?id=com.smapps.desi_maal_hd"
	},
	{
		"appIcon": "https://play-lh.googleusercontent.com/fTmNTxrRtXqRaltdBWSAg2ru7-x5NeAPpoantz-GGShy1-vJfOw0XTMyfX4GCdcK9Yw=s180",
		"appName": "১৬ ডিসেম্বর ফটো ফ্রেম",
		"appDescription": "বিজয় দিবস ফটো ফ্রেম",
		"url": "https://play.google.com/store/apps/details?id=com.bijoy_dibosh.photo_frame"
	},
	{
		"appIcon": "https://play-lh.googleusercontent.com/3UtJj3aeJwWwOY3WK99sw1ambrVv-bGq-Ivl7c60S3yIT96lNJZmaSK4-uTGtRCQhQ=s180",
		"appName": "২১শে ফেব্রুয়ারি ফটো ফ্রেম",
		"appDescription": "২১শে ফেব্রুয়ারি মাতৃভাষা দিবসের ফটো ফ্রেম",
		"url": "https://play.google.com/store/apps/details?id=com.ekushe_february.photo_frame"
	},
	{
		"appIcon": "https://play-lh.googleusercontent.com/SQtW0BueDfjORX3ELAZkklWyhQ5W0RvPI6FW-G7LIPFV9Fg2CDO8MIOSoxZCTDihn59y=s180",
		"appName": "New Year Photo Editor",
		"appDescription": "Happy New Year Photo Frames 2021",
		"url": "https://play.google.com/store/apps/details?id=com.new_year.photo_editor"
	},
	{
		"appIcon": "https://play-lh.googleusercontent.com/9Ktjolc0mEbYJmvX0TTUIPYw37fM1N26DpwSJAfer2t1UR6C5KHu90lG6y790bDIUF0=s180-rw",
		"appName": "Christmas Photo Editor",
		"appDescription": "Christmas Photo Frame 2021",
		"url": "https://play.google.com/store/apps/details?id=com.christmas.photo_editor"
	},
	{
		"appIcon": "https://lh3.googleusercontent.com/G-FiWFuj5sD7IWJKUnEqIZRGD-8LToHeiiCgpzQTzjslfx_g6vvFe0Lgw-XvsUlYRA=s180-rw",
		"appName": "Hall Photo Frames 3D",
		"appDescription": "Hall & Home Interior Photo Editor",
		"url": "https://play.google.com/store/apps/details?id=com.photo_frame.hall"
	},
	{
		"appIcon": "https://lh3.googleusercontent.com/PJmQJXlDmHZ-ifWDJqkIovzHyqp6ndi7y7grUQlhHj5UvJMD5JrjDD9w1cbDJODNToQF=s180-rw",
		"appName": "Hoarding Photo Frames",
		"appDescription": "Street Hoarding Photo Frames Editor",
		"url": "https://play.google.com/store/apps/details?id=com.photo_frames.hoarding"
	},
	
	{
		"appIcon": "https://lh3.googleusercontent.com/MDGtpmdFinDVZ0IXNXamoFX5HDPlmDGTwC9ooHecfLOXKGOZPmUcUrWJIeRB2KrwlGia=s180-rw",
		"appName": "Bollywood Photo Frames",
		"appDescription": "Bollywood Actors & Actresses Photo Editor",
		"url": "https://play.google.com/store/apps/details?id=com.photo_frame.bollywood"
	},
		{
		"appIcon": "https://lh3.googleusercontent.com/Dc4sXb9GV-mq_GFiCutPcwv2YUVca8Q4ffrmXW1qB7npL50c4i-l3iUqS5db2MT8ww3Z=s180-rw",
		"appName": "Mobile Photo Frames",
		"appDescription": "Mobile Phone & Selfie Photo Editor",
		"url": "https://play.google.com/store/apps/details?id=com.mobile.photo_frame"
	},
	{
		"appIcon": "https://lh3.googleusercontent.com/WXMFhzlj1poAbYi5fqqOczQW9BIrxRUl-gtrjud_x-vsWKZ48sAkrDgf6GFagaBwSfs=s180-rw",
		"appName": "TajMahal Photo Frame",
		"appDescription": "Taj Mahal Photo Editor",
		"url": "https://play.google.com/store/apps/details?id=com.photo_frame.tajmahal"
	},
	{
		"appIcon": "https://play-lh.googleusercontent.com/MRs6o9r6tvTTl8YMWU_Pa1ePP3nhwoKgDd4j7rGuQ8LnQiu8ASDHftbdbdtKKJruvo4=s180",
		"appName": "Bangladeshi Frame",
		"appDescription": "সকল দিবসের প্রোফাইল ফ্রেম",
		"url": "https://play.google.com/store/apps/details?id=com.SMdev.photo_frame"
	},
	{
		"appIcon": "https://lh3.googleusercontent.com/ZGJmfWAzMsfCoL0e_KMcuJKmUDNqGEOBgXVmsbde7LuwUkacW3yOIsjCd7-sWARKxqyA=s180-rw",
		"appName": "Birthday Photo Frames",
		"appDescription": "Birthday Wishing Photo Editor App",
		"url": "https://play.google.com/store/apps/details?id=com.photo_frame.birthday"
	},
	
	{
		"appIcon": "https://lh3.googleusercontent.com/LvzXWuxo7M2XxXzGvWCMFBF9gfjEkUwJ4nYx_4m-yalRnL9fOzz1AZvBHCn82hB4jA=s180",
		"appName": "Couple Love Frames",
		"appDescription": "Decorate your memories with Romantic Love Photo Frame.",
		"url": "https://play.google.com/store/apps/details?id=com.photo_frame.love"
	},
	
	{
		"appIcon": "https://lh3.googleusercontent.com/mNO8K330F3YPUIMAzKG3l5sGRTvBPrqYy6dKDXAtbIAvqANT0MwRMZmZ4Fj_Lj-j52g=s180",
		"appName": "কবিরা গুনাহ ও মুক্তির উপায়",
		"appDescription": "Kabira Gunah in Islam.",
		"url": "https://play.google.com/store/apps/details?id=com.smapps.kabira_gunah"
	},

	{
		"appIcon": "https://play-lh.googleusercontent.com/SQtW0BueDfjORX3ELAZkklWyhQ5W0RvPI6FW-G7LIPFV9Fg2CDO8MIOSoxZCTDihn59y=s180",
		"appName": "New Year Photo Editor",
		"appDescription": "Happy New Year Photo Frames 2021",
		"url": "https://play.google.com/store/apps/details?id=com.new_year.photo_editor"
	},
	{
		"appIcon": "https://lh3.googleusercontent.com/LqLddUjf2p3Qers7ekA7rXvNHe8yVNtwypRiq7UrYCwRIO_OedlKekfDXiLSxg2V73w=s180",
		"appName": "স্তন ক্যান্সার ও স্তনের সমস্যাসমূহ",
		"appDescription": "স্তন ক্যান্সার, স্তনের সমস্যাসমূহ ও ব্রা এর সঠিক ব্যবহার ও উপকারিতা",
		"url": "https://play.google.com/store/apps/details?id=com.BreastCancer.health"
	},
	{
		"appIcon": "https://lh3.googleusercontent.com/4ib0FPLqMwS5jw7-lW_BIRAeniiO6CYFx_Qr53vqX35-58O1W4Rgn5vhmfsvbOFlEjA=s180",
		"appName": "বুকের দুধ বাড়ানোর উপায়",
		"appDescription": "How to increase breast milk",
		"url": "https://play.google.com/store/apps/details?id=com.smapps.increse_breasts_milk"
	},
        {
		"appIcon": "https://lh3.googleusercontent.com/5BxfOGD39RQM5VPF41bXVtgNn7efKJHUBT2K4Rf5gKvo54zxnctC0YVvVyRaxRY6rYsY=s180-rw",
		"appName": "কোন নামের মেয়ে কেমন হয়",
		"appDescription": "Kon Naam Er Meye Kemon",
		"url": "https://play.google.com/store/apps/details?id=com.SMapps.kon_naam_er_meyera_kemon"
	},

	{
		"appIcon": "https://lh3.googleusercontent.com/Hq2bTUAyMtbccWzfTrlpXqnGXIGpC43jvdVaxDd5O6Vizzs5XDn74rgJ_D0qWZ6TG7I=s180",
		"appName": "বিখ্যাত ব্যক্তিদের উক্তি",
		"appDescription": "বিখ্যাত ব্যক্তিদের উক্তি / বাণী এর বিশাল সংগ্রহ।",
		"url": "https://play.google.com/store/apps/details?id=com.BikkhatoUkti.Bangla"
	},
	
	{
		"appIcon": "https://lh3.googleusercontent.com/4_Zmxglso_jDs3-IO6X4a3OGJcOxqYFNmJAh9mringO4TGTbNKkjSSlYDPrwVuJF-YM=s180",
		"appName": "বাংলা স্ট্যাটাস ও উক্তি",
		"appDescription": "সকল প্রকার বাংলা উক্তি, এসএমএস ও স্ট্যাটাস",
		"url": "https://play.google.com/store/apps/details?id=com.status_sms.bangla"
	},
	
	{
		"appIcon": "https://lh3.googleusercontent.com/XO5mCcOlKZdZJcbTiQLzCtGneRYgBVokY-gm2TIkKaR3lcY5Rae5DcU1XN3WCEn_xSp9=s180-rw",
		"appName": "SwagWord - Fancy Text",
		"appDescription": "Stylish Text Fonts Generator",
		"url": "https://play.google.com/store/apps/details?id=com.swag.stylish.word"
	},
	
	{
		"appIcon": "https://lh3.googleusercontent.com/Wmb8lSKd2aAxYF7reunWAicwe3YuOzS6khqQUNH4lhyEEdbUojPQ2I0vpduNSU5R-S4=s180",
		"appName": "Joy Bangla Photo Frame",
		"appDescription": "জয় বাংলা ও আওয়ামী লীগ ফটো ফ্রেম",
		"url": "https://play.google.com/store/apps/details?id=com.joy_bangla.photo_frame"
	},
	{
		"appIcon": "https://lh3.googleusercontent.com/jAjDENLlVLxDH8aQTXjbKsDikQ3WSq8inPT0-DtINbAOXC5sUhQqArq-NBMclMRQ_g4=s180",
		"appName": "হস্তমৈথুন ছাড়ার উপায়",
		"appDescription": "হস্থমৈথুনের সম্পর্কে জানার জন্য অ্যাপস টি ডাউনলোড করুন।",
		"url": "https://play.google.com/store/apps/details?id=com.smapps.hostomoithun"
	}
	
]
